sphinxcontrib_django2/__init__.py
sphinxcontrib_django2-1.9.dist-info/LICENSE
sphinxcontrib_django2-1.9.dist-info/METADATA
sphinxcontrib_django2-1.9.dist-info/WHEEL
sphinxcontrib_django2-1.9.dist-info/top_level.txt
sphinxcontrib_django2-1.9.dist-info/RECORD
