Metadata-Version: 2.1
Name: sphinxcontrib-django2
Version: 1.9
Summary: The changes of this fork have been merged into the original package sphinxcontrib-django.
Author-email: Timo Ludwig <ti.ludwig@web.de>
License: Apache2 2.0 License
Project-URL: Bug Tracker, https://github.com/timoludwig/sphinxcontrib-django2/issues
Project-URL: Documentation, https://sphinxcontrib-django2.readthedocs.io/
Project-URL: Release Notes, https://github.com/timoludwig/sphinxcontrib-django2/blob/develop/CHANGES.rst
Project-URL: Source Code, https://github.com/timoludwig/sphinxcontrib-django2
Project-URL: Upstream Package, https://pypi.python.org/pypi/sphinxcontrib-django/
Project-URL: Upstream Source Code, https://github.com/edoburu/sphinxcontrib-django
Requires-Python: >=3.7
License-File: LICENSE
Requires-Dist: sphinxcontrib-django
Provides-Extra: doc
Requires-Dist: sphinx-last-updated-by-git ; extra == 'doc'
Requires-Dist: sphinx-rtd-theme ; extra == 'doc'
